django_redbeat/__init__.py
django_redbeat/admin.py
django_redbeat/apps.py
django_redbeat/models.py
django_redbeat/signals.py
django_redbeat/tests.py
django_redbeat/views.py
django_redbeat/migrations/0001_initial.py
django_redbeat/migrations/__init__.py
django_redbeat-0.3.dist-info/LICENSE
django_redbeat-0.3.dist-info/METADATA
django_redbeat-0.3.dist-info/WHEEL
django_redbeat-0.3.dist-info/top_level.txt
django_redbeat-0.3.dist-info/RECORD
