Metadata-Version: 2.1
Name: django-redbeat
Version: 0.3
Summary: A Django app to add dynamic celery redbeat periodic tasks
Home-page: https://github.com/parad0x96/django-redbeat
Author: Karim Bourahla
Author-email: k.bourahla0x@gmail.com
License: MIT license
Classifier: Environment :: Web Environment
Classifier: Framework :: Django
Classifier: Framework :: Django :: 3.2
Classifier: Intended Audience :: Developers
Classifier: License :: OSI Approved :: MIT License
Classifier: Operating System :: OS Independent
Classifier: Programming Language :: Python
Classifier: Programming Language :: Python :: 3
Classifier: Topic :: Internet :: WWW/HTTP
Classifier: Topic :: Internet :: WWW/HTTP :: Dynamic Content
Requires-Python: >=3.6
License-File: LICENSE
Requires-Dist: Django (>=3.2)
